{
	"clbid": "0000020153",
	"credits": 0.25,
	"crsid": "0000000211",
	"departments": [
		"CHEM"
	],
	"enroll": 3,
	"instructors": [
		"Gary Miessler"
	],
	"level": 300,
	"max": 999,
	"name": "Advanced Lab",
	"number": 375,
	"pn": true,
	"prerequisites": false,
	"revisions": [
		{
			"_updated": "2018-07-12T16:49:26.552683+00:00",
			"enroll": null,
			"max": null
		},
		{
			"_updated": "2018-08-07T14:46:07.485701+00:00",
			"enroll": "3",
			"max": "999"
		}
	],
	"semester": 3,
	"status": "O",
	"term": 19963,
	"type": "Lab",
	"year": 1996
}
