{
	"clbid": 79710,
	"credits": 1.0,
	"crsid": 13,
	"depts": [
		"AMST"
	],
	"desc": "This course undertakes an intensive study of a particular period or topic through the interdisciplinary perspective of American studies. This course employs a seminar format, with concentration on student research. Recent topics include: \"Disney's America,\" \"American Women of Color,\" \"Man and Nature,\" and \"California Dreams.\" Offered annually in the spring semester. May be repeated if topics are different.",
	"instructors": [
		"Mark Allister"
	],
	"level": 300,
	"locations": [
		"TOH 212",
		"TOH 212"
	],
	"name": "Sem: 1968 Am Revolutions",
	"notes": "Limited to American Studies majors. All other students by consent of instructor only.",
	"num": 301,
	"pf": false,
	"prerequisites": false,
	"semester": 3,
	"status": "O",
	"term": 20113,
	"times": [
		"T 1145-0110PM",
		"Th 1245-0205PM"
	],
	"title": "Seminar",
	"type": "Seminar",
	"year": 2011
}
