{
	"clbid": "0000102390",
	"credits": 1.0,
	"crsid": "0000001239",
	"department": "REL",
	"enrolled": 1,
	"instructors": [
		"Jamie A. Schillinger"
	],
	"level": 200,
	"max": 0,
	"name": "IS/Lib Theo & Israel Pale",
	"number": 298,
	"pn": false,
	"prerequisites": false,
	"revisions": [
		{
			"_updated": "2018-07-12T16:51:22.144658+00:00",
			"enroll": null,
			"max": null
		},
		{
			"_updated": "2018-08-07T14:48:15.573915+00:00",
			"enroll": "1",
			"max": "999"
		},
		{
			"_updated": "2020-09-18T15:03:49.464955+00:00",
			"max": 999
		}
	],
	"section": "A",
	"semester": 2,
	"status": "O",
	"term": 20142,
	"title": "Independent Study",
	"type": "Research",
	"year": 2014
}
