{
	"clbid": "0000004717",
	"credits": 0.5,
	"crsid": "0000000021",
	"department": "ART",
	"enrolled": 22,
	"firstyear": "2/2",
	"instructors": [
		"Jil Evans"
	],
	"junior": "6/7",
	"level": 100,
	"max": 22,
	"name": "Found Color Design",
	"number": 113,
	"offerings": [
		{
			"day": "Tu",
			"end": "14:45",
			"location": "CAD 116",
			"start": "13:20"
		},
		{
			"day": "Th",
			"end": "15:35",
			"location": "CAD 116",
			"start": "14:15"
		}
	],
	"pn": false,
	"prerequisites": false,
	"revisions": [
		{
			"_updated": "2017-05-30T15:39:56.824680+00:00",
			"locations": [
				"DC 116",
				"DC 116"
			]
		},
		{
			"_updated": "2018-07-12T16:49:58.821812+00:00",
			"enroll": null,
			"max": null
		},
		{
			"_updated": "2018-08-07T14:46:43.135406+00:00",
			"enroll": "22",
			"max": "22"
		},
		{
			"_updated": "2018-10-19T04:11:15.876223+00:00",
			"firstyear": null,
			"junior": null,
			"senior": null,
			"sophomore": null
		}
	],
	"section": "A",
	"semester": 3,
	"senior": "13/4",
	"sophomore": "1/2",
	"status": "C",
	"term": 20023,
	"type": "Research",
	"year": 2002
}
