{
	"clbid": "0000089500",
	"credits": 1.0,
	"crsid": "0000000967",
	"department": "PHIL",
	"description": [
		"This course introduces philosophical ideas and methods through reading, discussing, and writing about basic questions that arise when we reflect on the human condition. What is meant by \"meaning\" when one asks whether (a person's) life has meaning? How do our beliefs about human nature, religion and morality affect how we ask or answer the question? How does our mortality affect our living? Classical and contemporary writings -- philosophical and autobiographical -- are used. Offered during Interim."
	],
	"enrolled": 19,
	"firstyear": "7/7",
	"instructors": [
		"Jason Marsh"
	],
	"junior": "1/2",
	"learningmode": "S",
	"level": 100,
	"max": 18,
	"name": "Death/Meaning of Life",
	"notes": [
		"This course has class-year limits."
	],
	"number": 147,
	"offerings": [
		{
			"day": "Mo",
			"end": "12:40",
			"location": "HH 516",
			"start": "10:40"
		},
		{
			"day": "Tu",
			"end": "12:40",
			"location": "HH 516",
			"start": "10:40"
		},
		{
			"day": "We",
			"end": "12:40",
			"location": "HH 516",
			"start": "10:40"
		},
		{
			"day": "Th",
			"end": "12:40",
			"location": "HH 516",
			"start": "10:40"
		},
		{
			"day": "Fr",
			"end": "12:40",
			"location": "HH 516",
			"start": "10:40"
		}
	],
	"pn": false,
	"prerequisites": false,
	"revisions": [
		{
			"_updated": "2018-07-12T16:51:13.547554+00:00",
			"enroll": null,
			"max": null
		},
		{
			"_updated": "2018-08-07T14:48:07.376995+00:00",
			"enroll": "19",
			"max": "18"
		},
		{
			"_updated": "2018-10-19T04:12:18.129925+00:00",
			"firstyear": null,
			"senior": null,
			"sophomore": null
		},
		{
			"_updated": "2018-10-28T04:14:54.092359+00:00",
			"firstyear": "6/2",
			"junior": null,
			"senior": "7/7",
			"sophomore": "1/2"
		},
		{
			"_updated": "2020-09-18T15:03:45.756622+00:00",
			"max": 18
		},
		{
			"_updated": "2020-10-15T15:23:49.514584+00:00",
			"learningmode": null
		},
		{
			"_updated": "2021-03-02T16:51:27.286527+00:00",
			"max": 19
		},
		{
			"_updated": "2025-10-11T21:36:13.165710+00:00",
			"gereqs": [
				"WRI"
			]
		}
	],
	"semester": 2,
	"senior": "6/2",
	"status": "C",
	"term": 20132,
	"title": "Death and the Meaning of Life",
	"type": "Research",
	"year": 2013
}
