{
	"clbid": 25992,
	"credits": 1.0,
	"crsid": 215,
	"departments": [
		"CHEM"
	],
	"enroll": 9,
	"instructors": [
		"Wesley Pearson"
	],
	"level": 300,
	"locations": [
		"SC 310",
		"SC 310"
	],
	"max": 999,
	"name": "Organic Analys/Theory",
	"number": 380,
	"pn": false,
	"prerequisites": false,
	"revisions": [
		{
			"_updated": "2018-07-12T16:49:41.263423+00:00",
			"enroll": null,
			"max": null
		},
		{
			"_updated": "2018-08-07T14:46:23.083984+00:00",
			"enroll": "9",
			"max": "999"
		}
	],
	"semester": 2,
	"status": "O",
	"term": 19992,
	"times": [
		"M-F 0800-1000",
		"M-F 1240-0330PM"
	],
	"type": "Research",
	"year": 1999
}
