{
	"clbid": "0000126590",
	"credits": 1.0,
	"crsid": "0000000745",
	"department": "MATH",
	"description": [
		"Students encounter the theory of calculus and develop tools for communicating mathematical ideas with technical accuracy and sophistication. The goal is mastery of the concepts (e.g., limit, continuity, derivatives, and integrals) necessary to verify such important results as the Fundamental Theorem of Calculus, the Mean Value Theorem, and the Bolzano-Weierstrass Theorem. Emphasis is on theory and on developing the ability to write proofs. Offered each semester. Counts toward computer science mjaor. Prerequisite: MATH 126 or MATH 128, and MATH 220. Permission of instructor required for first-year students."
	],
	"enrolled": 19,
	"gereqs": [
		"WRI"
	],
	"instructors": [
		"David P. Walmsley"
	],
	"level": 200,
	"max": 18,
	"name": "Real Analysis I",
	"number": 244,
	"offerings": [
		{
			"day": "Mo",
			"end": "12:45",
			"location": "TOH 182",
			"start": "11:50"
		},
		{
			"day": "We",
			"end": "12:45",
			"location": "TOH 182",
			"start": "11:50"
		},
		{
			"day": "Fr",
			"end": "12:45",
			"location": "TOH 182",
			"start": "11:50"
		}
	],
	"pn": false,
	"prerequisites": "MATH 126 or MATH 128, and MATH 220. Permission of instructor required for first-year students.",
	"revisions": [
		{
			"_updated": "2019-02-13T05:07:42.237985+00:00",
			"instructors": [
				"Bruce Hanson"
			]
		},
		{
			"_updated": "2019-03-07T05:14:54.852873+00:00",
			"instructors": [
				"Staff"
			]
		},
		{
			"_updated": "2019-10-13T07:16:42.737457+00:00",
			"offerings": [
				{
					"day": "Mo",
					"end": "12:45",
					"location": "RNS 210",
					"start": "11:50"
				},
				{
					"day": "We",
					"end": "12:45",
					"location": "RNS 210",
					"start": "11:50"
				},
				{
					"day": "Fr",
					"end": "12:45",
					"location": "RNS 210",
					"start": "11:50"
				}
			]
		},
		{
			"_updated": "2019-10-16T07:18:47.111388+00:00",
			"offerings": [
				{
					"day": "Mo",
					"end": "12:45",
					"location": "TOH 184",
					"start": "11:50"
				},
				{
					"day": "We",
					"end": "12:45",
					"location": "TOH 184",
					"start": "11:50"
				},
				{
					"day": "Fr",
					"end": "12:45",
					"location": "TOH 184",
					"start": "11:50"
				}
			]
		},
		{
			"_updated": "2019-11-07T07:32:38.966478+00:00",
			"enrolled": 0,
			"status": "O"
		},
		{
			"_updated": "2020-01-05T08:03:16.182130+00:00",
			"enrolled": 18
		},
		{
			"_updated": "2020-01-11T08:06:17.580555+00:00",
			"enrolled": 19
		},
		{
			"_updated": "2020-01-24T08:13:48.587967+00:00",
			"enrolled": 18
		}
	],
	"section": "B",
	"semester": 3,
	"status": "C",
	"term": 20193,
	"type": "Research",
	"year": 2019
}
