{
	"clbid": 11112,
	"credits": 1.0,
	"crsid": 1384,
	"departments": [
		"THEAT"
	],
	"description": [
		"A studio course for the student with previous acting experience. Through scene and monologue work students explore text and character analysis as well as the requirements of major theatrical period styles. Students perform regularly throughout the semester. Prerequisites: Theatre 110 and 130. Offered Fall Semester only."
	],
	"instructors": [
		"Dona W. Freeman"
	],
	"level": 200,
	"locations": [
		"TB Haugen",
		"TB Haugen"
	],
	"name": "Intermediate Acting",
	"number": 230,
	"pn": false,
	"prerequisites": "Prerequisites: Theatre 110 and 130. Offered Fall Semester only.",
	"semester": 1,
	"status": "O",
	"term": 20051,
	"times": [
		"T 0120-0245PM",
		"Th 0215-0335PM"
	],
	"type": "Research",
	"year": 2005
}
