{
	"clbid": "0000003499",
	"credits": 1.0,
	"crsid": "0000001258",
	"department": "REL",
	"enrolled": 7,
	"instructors": [
		"Philip E. Stoltzfus"
	],
	"learningmode": "S",
	"level": 300,
	"max": 15,
	"name": "Them Sem: Theol,Music",
	"number": 399,
	"offerings": [
		{
			"day": "Tu",
			"end": "14:45",
			"location": "CH 109",
			"start": "13:20"
		},
		{
			"day": "Th",
			"end": "14:45",
			"location": "CH 109",
			"start": "13:20"
		}
	],
	"pn": false,
	"prerequisites": false,
	"revisions": [
		{
			"_updated": "2018-07-12T16:49:54.141997+00:00",
			"enroll": null,
			"max": null
		},
		{
			"_updated": "2018-08-07T14:46:37.625749+00:00",
			"enroll": "7",
			"max": "15"
		},
		{
			"_updated": "2019-12-06T07:46:56.348568+00:00",
			"type": "Research"
		},
		{
			"_updated": "2020-10-15T15:23:09.211497+00:00",
			"learningmode": null
		}
	],
	"semester": 3,
	"status": "O",
	"term": 20013,
	"type": "Seminar",
	"year": 2001
}
