{
	"clbid": 108966,
	"credits": 1.0,
	"crsid": 20072,
	"depts": [
		"WRIT"
	],
	"desc": "Blending the reading seminar and writing workshop, this course offers advanced practice in critical reading and writing with emphasis on a particular discipline or topic. Students will read and respond critically to a range of writing that may include textbook chapters, popular feature stories, and creative literature. The course emphasizes how writers make and support claims, integrate research, and narrate to communicate effectively in a variety of genres for multiple audiences. Click on course title in the class and lab for more information about the course for that term. Prequisite: successful completion of FYW.",
	"gereqs": [
		"WRI"
	],
	"instructors": [
		"Diane C. LeBlanc"
	],
	"level": 200,
	"locations": [
		"TBA"
	],
	"name": "Top: Sci in World & Word",
	"notes": "Prerequisite: completion of FYW requirement.",
	"num": 211,
	"pf": false,
	"prerequisites": "Prerequisite: completion of FYW requirement.",
	"revisions": [
		{
			"_updated": "2016-04-25T16:47:19.169104-05:00",
			"locations": []
		}
	],
	"semester": 3,
	"status": "O",
	"term": 20163,
	"times": [
		"MWF 1255-0150PM"
	],
	"title": "Topics in Writing",
	"type": "Topic",
	"year": 2016
}
