{
	"clbid": "0000115262",
	"credits": 1.0,
	"crsid": "0000000857",
	"department": "MUSIC",
	"description": [
		"Students encounter in-depth studies in a specific topic or area of music history. The content and nature of this course are determined by the instructor and the music department. Sample topics include American music, studies in classical music, opera, and folk and pop influences in art music. May be repeated if topic is different. Offered each semester. Prerequisites: MUSIC 241 and MUSIC 242."
	],
	"enroll": 8,
	"instructors": [
		"Louis K. Epstein"
	],
	"level": 300,
	"locations": [
		"CHM 239",
		"CHM 239"
	],
	"max": 19,
	"name": "Top: Gender in Opera",
	"number": 345,
	"pn": false,
	"prerequisites": "Prerequisites: MUSIC 241 and MUSIC 242.",
	"revisions": [
		{
			"_updated": "2017-10-05T01:13:50.606964+00:00",
			"locations": null
		},
		{
			"_updated": "2017-10-12T01:16:50.413558+00:00",
			"section": null
		},
		{
			"_updated": "2017-11-15T01:34:02.223126+00:00",
			"locations": [
				"CHM 239"
			],
			"times": [
				"M-F 0100-0300PM"
			]
		},
		{
			"_updated": "2018-07-12T16:51:46.011893+00:00",
			"enroll": null,
			"max": null
		},
		{
			"_updated": "2018-08-07T14:48:39.132003+00:00",
			"enroll": "8",
			"max": "19"
		}
	],
	"section": "A",
	"semester": 2,
	"status": "O",
	"term": 20172,
	"times": [
		"M-F 1040-1200PM",
		"M-F 0100-0400PM"
	],
	"title": "Advanced Study in Music History",
	"type": "Topic",
	"year": 2017
}
