{
	"clbid": "0000115669",
	"credits": 1.0,
	"crsid": "0000001064",
	"department": "ESTH",
	"description": [
		"Students study in-depth the physiology of exercise, covering cardiovascular and muscular adaptions to exercise and factors affecting performance, including body composition, environmental influences, training implications across gender and age, and the assessment of fitness. The course includes a laboratory component. Offered annually. Counts toward neuroscience concentration. Prerequisite: junior standing and BIO 143 and BIO 243 or permission of instructor."
	],
	"enrolled": 17,
	"groupid": "0000001064",
	"instructors": [
		"Jennifer M. Holbein"
	],
	"learningmode": "S",
	"level": 300,
	"max": 24,
	"name": "Physiology/Exercise",
	"notes": [
		"This course includes an academic civic engagement (ACE) component."
	],
	"number": 375,
	"offerings": [
		{
			"day": "Mo",
			"end": "11:40",
			"location": "SAC 103",
			"start": "10:45"
		},
		{
			"day": "We",
			"end": "11:40",
			"location": "SAC 103",
			"start": "10:45"
		},
		{
			"day": "Fr",
			"end": "11:40",
			"location": "SAC 103",
			"start": "10:45"
		}
	],
	"pn": false,
	"prerequisites": "junior standing and BIO 143 and BIO 243 or permission of instructor.",
	"revisions": [
		{
			"_updated": "2017-05-09T23:50:31.256964+00:00",
			"instructors": [
				"Staff"
			]
		},
		{
			"_updated": "2017-10-24T01:23:59.607862+00:00",
			"notes": null
		},
		{
			"_updated": "2018-02-03T00:03:29.256802+00:00",
			"prerequisites": "Prerequisite: junior standing and BIO 143 and BIO 243 or permission of instructor."
		},
		{
			"_updated": "2018-07-12T16:51:44.837046+00:00",
			"enroll": null,
			"max": null
		},
		{
			"_updated": "2018-08-07T14:48:37.707676+00:00",
			"enroll": "17",
			"max": "24"
		},
		{
			"_updated": "2020-10-15T15:24:03.596158+00:00",
			"learningmode": null
		}
	],
	"semester": 1,
	"status": "O",
	"term": 20171,
	"title": "Physiology of Exercise",
	"type": "Research",
	"year": 2017
}
