{
	"clbid": 96058,
	"credits": 1.0,
	"crsid": 920,
	"depts": [
		"NEURO"
	],
	"instructors": [
		"Kevin M. Crisp"
	],
	"level": 300,
	"name": "IR/Wireless Neuro Device",
	"num": 398,
	"pf": false,
	"prerequisites": false,
	"revisions": [
		{
			"_updated": "2015-10-31T00:23:18.192950-05:00",
			"instructors": [
				"Staff"
			],
			"name": "IR/"
		},
		{
			"_updated": "2016-01-30T09:05:06.847624-06:00",
			"title": null
		}
	],
	"semester": 3,
	"status": "O",
	"term": 20143,
	"title": "Independent Research",
	"type": "Research",
	"year": 2014
}
