{
	"clbid": "0000091006",
	"credits": 1.0,
	"crsid": "0000000709",
	"department": "ID",
	"enrolled": 1,
	"instructors": [
		"Maria L. Kelly"
	],
	"learningmode": "S",
	"level": 300,
	"max": 0,
	"name": "Academic Internship",
	"number": 394,
	"pn": true,
	"prerequisites": false,
	"revisions": [
		{
			"_updated": "2018-07-12T16:51:06.864809+00:00",
			"enroll": null,
			"max": null
		},
		{
			"_updated": "2018-08-07T14:48:00.165422+00:00",
			"enroll": "1",
			"max": "999"
		},
		{
			"_updated": "2020-09-18T15:03:42.253428+00:00",
			"max": 999
		},
		{
			"_updated": "2020-10-15T15:23:45.925258+00:00",
			"learningmode": null
		}
	],
	"section": "A",
	"semester": 2,
	"status": "O",
	"term": 20122,
	"type": "Research",
	"year": 2012
}
