{
	"clbid": "0000091209",
	"credits": 1.0,
	"crsid": "0000000229",
	"departments": [
		"CLASS"
	],
	"description": [
		"For the Greeks and Romans myth was a cultural reality, just as it is for us. Students in this course read the famous tales told by the poets Homer, Hesiod, Aeschylus, Sophocles, Euripides, Vergil, and Ovid, and ponder the deeper truths contained in their works of fiction. The class also explores the use of classical myth in later literature and its manifestations in art, music, and drama from ancient to modern times. Offered annually. Counts towards ancient studies major."
	],
	"enroll": 24,
	"gereqs": [
		"ALS-L"
	],
	"instructors": [
		"Steve T. Reece"
	],
	"level": 200,
	"locations": [
		"TOH 312",
		"TOH 312"
	],
	"max": 25,
	"name": "Greek & Roman Myth-Tr",
	"number": 241,
	"pn": false,
	"prerequisites": false,
	"revisions": [
		{
			"_updated": "2018-07-12T16:51:15.731379+00:00",
			"enroll": null,
			"max": null
		},
		{
			"_updated": "2018-08-07T14:48:09.782657+00:00",
			"enroll": "24",
			"max": "25"
		}
	],
	"semester": 3,
	"status": "C",
	"term": 20133,
	"times": [
		"T 1145-0110PM",
		"Th 1245-0205PM"
	],
	"title": "Greek and Roman Myth",
	"type": "Research",
	"year": 2013
}
