{
	"clbid": "0000163595",
	"credits": 1.0,
	"crsid": "0000036173",
	"department": "FYS",
	"description": [
		"This course emphasizes critical thinking, conversation, collaboration, and academic habits for the liberal arts. Students learn key skills like locating and evaluating academic sources, as well as reading, reflecting, and responding to texts. Students cultivate their own curiosity while also learning how to engage in community, better understanding their responsibilities to each other. This course is open to first-year students and a limited number of sophomores. Prerequisite: first-year student status."
	],
	"enrolled": 0,
	"gereqs": [
		"FYS"
	],
	"groupid": "0000036173",
	"grouptype": "M",
	"instructors": [
		"Colin Wells"
	],
	"junior": "0/0",
	"learningmode": "S",
	"level": 100,
	"max": 18,
	"name": "Top: The 1960s Through Music",
	"notes": [
		"Section topic: The 1960s Through Music"
	],
	"number": 120,
	"offerings": [
		{
			"day": "Mo",
			"end": "12:45",
			"location": "CAD 202",
			"start": "11:50"
		},
		{
			"day": "We",
			"end": "12:45",
			"location": "CAD 202",
			"start": "11:50"
		},
		{
			"day": "Fr",
			"end": "12:45",
			"location": "CAD 202",
			"start": "11:50"
		}
	],
	"pn": false,
	"prerequisites": "first-year student status.",
	"revisions": [
		{
			"_updated": "2025-02-13T02:49:19.608998+00:00",
			"instructors": [
				"David Carter"
			],
			"notes": [
				"Section topic: Race in 20th Century Music"
			],
			"offerings": [
				{
					"day": "Mo",
					"end": "08:55",
					"location": "CHM 239",
					"start": "08:00"
				},
				{
					"day": "We",
					"end": "08:55",
					"location": "CHM 239",
					"start": "08:00"
				},
				{
					"day": "Fr",
					"end": "08:55",
					"location": "CHM 239",
					"start": "08:00"
				}
			],
			"section": "G"
		},
		{
			"_updated": "2025-02-22T02:44:43.018490+00:00",
			"firstyear": null,
			"max": 20,
			"name": "Top: Race in 20th Century Music",
			"section": "L",
			"sophomore": null
		},
		{
			"_updated": "2025-03-08T02:30:01.421745+00:00",
			"junior": null,
			"senior": null,
			"sophomore": "0/0"
		},
		{
			"_updated": "2025-03-22T02:54:00.526024+00:00",
			"grouptype": "G"
		},
		{
			"_updated": "2025-04-16T03:04:25.178429+00:00",
			"name": "Top: First-Year Seminar",
			"notes": null
		},
		{
			"_updated": "2025-05-03T03:02:54.762717+00:00",
			"offerings": [
				{
					"day": "Mo",
					"end": "12:45",
					"location": "TBA",
					"start": "11:50"
				},
				{
					"day": "We",
					"end": "12:45",
					"location": "TBA",
					"start": "11:50"
				},
				{
					"day": "Fr",
					"end": "12:45",
					"location": "TBA",
					"start": "11:50"
				}
			]
		},
		{
			"_updated": "2025-05-08T03:11:14.018609+00:00",
			"offerings": [
				{
					"day": "Fr",
					"end": "12:45",
					"location": "CAD 202",
					"start": "11:50"
				},
				{
					"day": "Mo",
					"end": "12:45",
					"location": "CAD 202",
					"start": "11:50"
				},
				{
					"day": "We",
					"end": "12:45",
					"location": "CAD 202",
					"start": "11:50"
				}
			]
		},
		{
			"_updated": "2025-06-04T03:18:24.766257+00:00",
			"firstyear": "0/0"
		}
	],
	"section": "M",
	"semester": 1,
	"senior": "0/0",
	"status": "O",
	"term": 20251,
	"title": "First-Year Seminar",
	"type": "Topic",
	"year": 2025
}
