{
	"clbid": "0000026591",
	"credits": 0.25,
	"crsid": "0000001989",
	"department": "MUSIC",
	"enrolled": 10,
	"instructors": [
		"Dan Dressen"
	],
	"learningmode": "S",
	"level": 200,
	"max": 20,
	"name": "French Lyric Diction",
	"number": 266,
	"offerings": [
		{
			"day": "Mo",
			"end": "12:45",
			"location": "CHM 239",
			"start": "11:50"
		},
		{
			"day": "Fr",
			"end": "12:45",
			"location": "CHM 239",
			"start": "11:50"
		}
	],
	"pn": false,
	"prerequisites": false,
	"revisions": [
		{
			"_updated": "2018-07-12T16:49:43.711764+00:00",
			"enroll": null,
			"max": null
		},
		{
			"_updated": "2018-08-07T14:46:24.848355+00:00",
			"enroll": "10",
			"max": "20"
		},
		{
			"_updated": "2020-10-15T15:23:03.490427+00:00",
			"learningmode": null
		}
	],
	"semester": 3,
	"status": "O",
	"term": 19993,
	"type": "Research",
	"year": 1999
}
