{
	"clbid": "0000080511",
	"credits": 1.0,
	"crsid": "0000000297",
	"department": "CSCI",
	"description": [
		"Students study features commonly found in computer programming languages and construct their own interpreters for an example programming language incorporating various language features they study throughout the course. Topics include programming language semantics, programming language translation, parsing, implementation of control structures and memory structures, abstraction mechanisms, and language translation systems and types. Prerequisites: Computer Science 241 and Computer Science 251, or permission of instructor. Offered alternate years."
	],
	"enrolled": 19,
	"instructors": [
		"Richard Allen"
	],
	"level": 200,
	"max": 30,
	"name": "Programming Languages",
	"number": 276,
	"offerings": [
		{
			"day": "Mo",
			"end": "13:50",
			"location": "RNS 203",
			"start": "12:55"
		},
		{
			"day": "We",
			"end": "13:50",
			"location": "RNS 203",
			"start": "12:55"
		},
		{
			"day": "Fr",
			"end": "13:50",
			"location": "RNS 203",
			"start": "12:55"
		}
	],
	"pn": false,
	"prerequisites": "Prerequisites: Computer Science 241 and Computer Science 251, or permission of instructor. Offered alternate years.",
	"revisions": [
		{
			"_updated": "2018-07-12T16:50:57.259259+00:00",
			"enroll": null,
			"max": null
		},
		{
			"_updated": "2018-08-07T14:47:50.413399+00:00",
			"enroll": "19",
			"max": "30"
		}
	],
	"semester": 1,
	"status": "O",
	"term": 20111,
	"type": "Research",
	"year": 2011
}
