{
	"department": "PSCI",
	"description": [
		"Students examine ethical issues related to family life in the United States. Topics include",
		"the nature and purpose of the family; a history of family structures and values; the family as",
		"a school of justice; and the relationship between the family and the state. Students explore a",
		"variety of theological and philosophical traditions, on such issues as marriage and divorce,",
		"contraception and abortion, parenting practices, and public policy."
	],
	"fullname": "Family Values",
	"number": 270,
	"section": "",
	"semester": 1,
	"shortname": "Family Values",
	"type": "R",
	"year": 2006
}
