{
	"clbid": "0000018710",
	"credits": 1.0,
	"crsid": "0000001377",
	"departments": [
		"THEAT"
	],
	"enroll": 20,
	"instructors": [
		"Kathleen Edelmayer"
	],
	"level": 100,
	"locations": [
		"SPT 216"
	],
	"max": 20,
	"name": "Public Speaking",
	"number": 120,
	"pn": false,
	"prerequisites": false,
	"revisions": [
		{
			"_updated": "2018-07-12T16:49:22.099135+00:00",
			"enroll": null,
			"max": null
		},
		{
			"_updated": "2018-08-07T14:46:02.921929+00:00",
			"enroll": "20",
			"max": "20"
		}
	],
	"section": "B",
	"semester": 3,
	"status": "C",
	"term": 19953,
	"times": [
		"TTh 0935-1100"
	],
	"type": "Research",
	"year": 1995
}
