{
	"clbid": "0000140313",
	"credits": 1.0,
	"crsid": "0000019728",
	"department": "ECON",
	"description": [
		"In this course students apply the models, insights, and analytical techniques of economics to a specific topic or economic problem. Topics vary from year to year. May be repeated if topic is different. Offered periodically. Prerequisites: one of ECON 110-121 or permission of instructor."
	],
	"enrolled": 0,
	"instructors": [
		"Douglas Mugabe"
	],
	"learningmode": "S",
	"level": 200,
	"max": 25,
	"name": "Top: Climate Economics",
	"number": 200,
	"offerings": [
		{
			"day": "Tu",
			"end": "09:25",
			"location": "TBA",
			"start": "08:00"
		},
		{
			"day": "Th",
			"end": "09:20",
			"location": "TBA",
			"start": "08:00"
		}
	],
	"pn": false,
	"prerequisites": "Prerequisites: one of ECON 110-121 or permission of instructor.",
	"revisions": [
		{
			"_updated": "2021-02-26T16:43:42.828467+00:00",
			"name": "Top: Topics in Econ Analysis"
		},
		{
			"_updated": "2021-03-02T16:51:57.075102+00:00",
			"max": 25
		},
		{
			"_updated": "2021-03-11T16:48:57.799276+00:00",
			"max": 0
		}
	],
	"semester": 1,
	"status": "O",
	"term": 20211,
	"title": "Topics in Economic Analysis",
	"type": "Topic",
	"year": 2021
}
