{
	"clbid": "0000150960",
	"credits": 1.0,
	"crsid": "0000000731",
	"department": "MATH",
	"description": [
		"This course introduces differential and integral calculus of functions of a single real variable, including trigonometric, exponential, and logarithmic functions. Derivatives, integrals, and differential equations are explored graphically, symbolically, and numerically. Applications of these topics are emphasized throughout the course. Offered each semester and periodically during January Term. Prerequisite: mathematics placement"
	],
	"enrolled": 21,
	"gereqs": [
		"AQR",
		"QCR"
	],
	"instructors": [
		"Curtis J. Balz"
	],
	"learningmode": "S",
	"level": 100,
	"max": 22,
	"name": "Calculus I",
	"notes": [
		"Course fee $26.50"
	],
	"number": 120,
	"offerings": [
		{
			"day": "Mo",
			"end": "12:45",
			"location": "RNS 204",
			"start": "11:50"
		},
		{
			"day": "We",
			"end": "12:45",
			"location": "RNS 204",
			"start": "11:50"
		},
		{
			"day": "Fr",
			"end": "12:45",
			"location": "RNS 204",
			"start": "11:50"
		}
	],
	"pn": false,
	"prerequisites": "mathematics placement",
	"revisions": [
		{
			"_updated": "2023-11-01T02:24:55.021075+00:00",
			"enrolled": 0
		},
		{
			"_updated": "2023-11-03T02:21:37.621742+00:00",
			"enrolled": 1
		},
		{
			"_updated": "2023-11-04T02:19:28.844827+00:00",
			"enrolled": 4,
			"status": "O"
		},
		{
			"_updated": "2023-11-17T02:26:48.473276+00:00",
			"enrolled": 22,
			"status": "C"
		},
		{
			"_updated": "2023-11-19T02:27:40.552268+00:00",
			"enrolled": 21,
			"status": "O"
		},
		{
			"_updated": "2023-11-29T02:26:13.638406+00:00",
			"enrolled": 22,
			"status": "C"
		}
	],
	"section": "C",
	"semester": 3,
	"status": "O",
	"term": 20233,
	"type": "Research",
	"year": 2023
}
